{
  "posted": [
    {
      "name": "Drift86",
      "date": "2026-06-03"
    },
    {
      "name": "Tell Me Why: Chapter 1",
      "date": "2026-06-03"
    },
    {
      "name": "LONESTAR",
      "date": "2026-06-03"
    },
    {
      "name": "Calico",
      "date": "2026-06-03"
    },
    {
      "name": "Spiritfarer: Farewell Edition",
      "date": "2026-06-03"
    },
    {
      "name": "Gravity Circuit",
      "date": "2026-06-03"
    },
    {
      "name": "Shadow of the Tomb Raider - Definitive Edition",
      "date": "2026-06-03"
    }
  ]
}
